django_middleware_request_id/__init__.py
django_middleware_request_id/admin.py
django_middleware_request_id/apps.py
django_middleware_request_id/log_filters.py
django_middleware_request_id/middlewares.py
django_middleware_request_id/models.py
django_middleware_request_id/tests.py
django_middleware_request_id/views.py
django_middleware_request_id/migrations/__init__.py
django_middleware_request_id-0.1.6.dist-info/licenses/LICENSE
django_middleware_request_id-0.1.6.dist-info/METADATA
django_middleware_request_id-0.1.6.dist-info/WHEEL
django_middleware_request_id-0.1.6.dist-info/top_level.txt
django_middleware_request_id-0.1.6.dist-info/RECORD
