Metadata-Version: 2.4
Name: django-middleware-request-id
Version: 0.1.6
Summary: The middleware detect if a client or the front reverse proxy server provides a X-Request-ID header, and get it as the request_id. If no such header is provided, it can provide a random value.
Author: rRR0VrFP
Maintainer: rRR0VrFP
License: MIT
Keywords: django-middleware-request-id
Classifier: Development Status :: 5 - Production/Stable
Classifier: Intended Audience :: Developers
Classifier: Topic :: Software Development :: Libraries :: Python Modules
Classifier: License :: OSI Approved :: MIT License
Classifier: Programming Language :: Python :: 3
Classifier: Programming Language :: Python :: 3 :: Only
License-File: LICENSE
Requires-Dist: django
Requires-Dist: django-middleware-global-request
Dynamic: author
Dynamic: classifier
Dynamic: description
Dynamic: description-content-type
Dynamic: keywords
Dynamic: license
Dynamic: license-file
Dynamic: maintainer
Dynamic: requires-dist
Dynamic: summary
